ilspy_mcp_server/__init__.py
ilspy_mcp_server/ilspy_wrapper.py
ilspy_mcp_server/models.py
ilspy_mcp_server/server.py
ilspy_mcp_server-0.1.1.dist-info/METADATA
ilspy_mcp_server-0.1.1.dist-info/WHEEL
ilspy_mcp_server-0.1.1.dist-info/entry_points.txt
ilspy_mcp_server-0.1.1.dist-info/licenses/LICENSE
ilspy_mcp_server-0.1.1.dist-info/RECORD
