Metadata-Version: 2.4
Name: ilspy-mcp-server
Version: 0.1.1
Summary: MCP Server for ILSpy .NET Decompiler
Project-URL: Homepage, https://github.com/Borealin/ilspy-mcp-server
Project-URL: Repository, https://github.com/Borealin/ilspy-mcp-server.git
Project-URL: Issues, https://github.com/Borealin/ilspy-mcp-server/issues
Author-email: Borealin <me@borealin.cn>
License: MIT
License-File: LICENSE
Keywords: csharp,decompiler,dotnet,ilspy,mcp,reverse-engineering
Classifier: Development Status :: 4 - Beta
Classifier: Intended Audience :: Developers
Classifier: License :: OSI Approved :: MIT License
Classifier: Programming Language :: Python :: 3
Classifier: Programming Language :: Python :: 3.8
Classifier: Programming Language :: Python :: 3.9
Classifier: Programming Language :: Python :: 3.10
Classifier: Programming Language :: Python :: 3.11
Classifier: Programming Language :: Python :: 3.12
Classifier: Topic :: Software Development :: Debuggers
Classifier: Topic :: Software Development :: Libraries :: Python Modules
Classifier: Topic :: System :: Software Distribution
Requires-Python: >=3.8
Requires-Dist: mcp>=0.1.0
Requires-Dist: pydantic>=2.0.0
